ipyeos/__init__.py
ipyeos/__main__.py
ipyeos/_eos.cpython-310-darwin.so
ipyeos/action_trace.py
ipyeos/args.py
ipyeos/block_log.py
ipyeos/block_state.py
ipyeos/blocks.py
ipyeos/chain.py
ipyeos/chain_exceptions.py
ipyeos/chainapi.py
ipyeos/chaintester.py
ipyeos/database.py
ipyeos/database_objects.py
ipyeos/debug.py
ipyeos/debug_server.py
ipyeos/eos.py
ipyeos/exec_result.py
ipyeos/helper.py
ipyeos/ipykernel_embed.py
ipyeos/ipython_embed.py
ipyeos/log.py
ipyeos/main.py
ipyeos/multi_index.py
ipyeos/native_modules.py
ipyeos/net.py
ipyeos/node.py
ipyeos/node_config.py
ipyeos/packed_transaction.py
ipyeos/packer.py
ipyeos/rate_limit.py
ipyeos/read_write_lock.py
ipyeos/resource_limit.py
ipyeos/rpc.py
ipyeos/rpc_server.py
ipyeos/run.py
ipyeos/server.py
ipyeos/signed_block.py
ipyeos/signed_transaction.py
ipyeos/snapshot.py
ipyeos/state_history.py
ipyeos/stop_process.py
ipyeos/structs.py
ipyeos/trace_api.py
ipyeos/transaction_trace.py
ipyeos/types.py
ipyeos/utils.py
ipyeos/uvicorn_server.py
ipyeos/worker.py
ipyeos/interfaces/Apply.py
ipyeos/interfaces/ApplyRequest.py
ipyeos/interfaces/IPCChainTester.py
ipyeos/interfaces/PushActions.py
ipyeos/interfaces/__init__.py
ipyeos/interfaces/constants.py
ipyeos/interfaces/ttypes.py
ipyeos/release/bin/ipyeos
ipyeos/release/lib/libchain_api.dylib
ipyeos/release/lib/libvm_api.dylib
ipyeos/tests/activate_kv.wasm
ipyeos/tests/deposit_withdraw_prototype.py
ipyeos/tests/test_chain.py
ipyeos/tests/test_eosio_system.py
ipyeos/tests/test_kv.py
ipyeos/tests/test_micropython.py
ipyeos/tests/test_powerup.py
ipyeos/tests/test_producers.py
ipyeos/tests/test_rex.py
ipyeos/tests/test_template.py
ipyeos/tests/contracts/eosio.bios/eosio.bios.abi
ipyeos/tests/contracts/eosio.bios/eosio.bios.wasm
ipyeos/tests/contracts/eosio.msig/eosio.msig.abi
ipyeos/tests/contracts/eosio.msig/eosio.msig.wasm
ipyeos/tests/contracts/eosio.system/eosio.system.abi
ipyeos/tests/contracts/eosio.system/eosio.system.wasm
ipyeos/tests/contracts/eosio.token/eosio.token.abi
ipyeos-0.4.9.dist-info/LICENSE
ipyeos-0.4.9.dist-info/METADATA
ipyeos-0.4.9.dist-info/WHEEL
ipyeos-0.4.9.dist-info/entry_points.txt
ipyeos-0.4.9.dist-info/top_level.txt
ipyeos-0.4.9.dist-info/RECORD
