Metadata-Version: 2.1
Name: ipyeos
Version: 0.4.9
Summary: IPYEOS project
Author: The IPYEOS Team
License: MIT
License-File: LICENSE
Requires-Dist: thrift >=0.16.0
Requires-Dist: pytest >=6.2.5
Requires-Dist: pyyaml
Requires-Dist: uvicorn
Requires-Dist: fastapi
Requires-Dist: pydantic
Requires-Dist: aiomonitor
Requires-Dist: uvloop
Requires-Dist: aiocache
